zhcevanstest/__init__.py
zhcevanstest/plotfunc.py
zhcevanstest-1.1.6.dist-info/METADATA
zhcevanstest-1.1.6.dist-info/WHEEL
zhcevanstest-1.1.6.dist-info/top_level.txt
zhcevanstest-1.1.6.dist-info/RECORD
