Metadata-Version: 2.1
Name: zhcevanstest
Version: 1.1.6
Summary: A package for plotting Konrads data
Author: evans.zhu
Author-email: evanszhu2001@gmail.com
Classifier: License :: OSI Approved :: MIT License
Classifier: Programming Language :: Python :: 3
Classifier: Programming Language :: Python :: 3.6
Classifier: Programming Language :: Python :: 3.7
Classifier: Programming Language :: Python :: 3.8
Classifier: Programming Language :: Python :: 3.9
Requires-Dist: numpy
Requires-Dist: matplotlib
